asyncstdlib/__init__.py
asyncstdlib/_core.py
asyncstdlib/_lrucache.py
asyncstdlib/_lrucache.pyi
asyncstdlib/_typing.py
asyncstdlib/_utility.py
asyncstdlib/asynctools.py
asyncstdlib/builtins.py
asyncstdlib/builtins.pyi
asyncstdlib/contextlib.py
asyncstdlib/contextlib.pyi
asyncstdlib/functools.py
asyncstdlib/functools.pyi
asyncstdlib/heapq.py
asyncstdlib/heapq.pyi
asyncstdlib/itertools.py
asyncstdlib/itertools.pyi
asyncstdlib/py.typed
asyncstdlib_fw-3.13.1.dist-info/METADATA
asyncstdlib_fw-3.13.1.dist-info/WHEEL
asyncstdlib_fw-3.13.1.dist-info/entry_points.txt
asyncstdlib_fw-3.13.1.dist-info/licenses/LICENSE
asyncstdlib_fw-3.13.1.dist-info/RECORD
