Metadata-Version: 2.1
Name: asyncstdlib-fw
Version: 3.13.1
Keywords: async,enumerate,itertools,builtins,functools,contextlib
Author-Email: =?utf-8?b?TWF4IEvDvGhu?= <maxfischer2781@gmail.com>
License: MIT License
Classifier: Development Status :: 5 - Production/Stable
Classifier: Framework :: AsyncIO
Classifier: Intended Audience :: Developers
Classifier: License :: OSI Approved :: MIT License
Classifier: Programming Language :: Python :: 3 :: Only
Classifier: Programming Language :: Python :: 3.8
Classifier: Programming Language :: Python :: 3.9
Classifier: Programming Language :: Python :: 3.10
Classifier: Programming Language :: Python :: 3.11
Classifier: Programming Language :: Python :: 3.12
Classifier: Programming Language :: Python :: 3.13
Project-URL: Documentation, https://asyncstdlib.readthedocs.io/en/latest/
Project-URL: Source, https://github.com/maxfischer2781/asyncstdlib
Requires-Python: >=3.8
Provides-Extra: test
Requires-Dist: pytest; extra == "test"
Requires-Dist: flake8; extra == "test"
Requires-Dist: flake8-bugbear; extra == "test"
Requires-Dist: black; implementation_name == "cpython" and extra == "test"
Requires-Dist: coverage; extra == "test"
Requires-Dist: pytest-cov; extra == "test"
Requires-Dist: flake8-2020; extra == "test"
Requires-Dist: mypy; implementation_name == "cpython" and extra == "test"
Provides-Extra: typetest
Requires-Dist: mypy; implementation_name == "cpython" and extra == "typetest"
Requires-Dist: pyright; extra == "typetest"
Requires-Dist: typing-extensions; extra == "typetest"
Provides-Extra: doc
Requires-Dist: sphinx; extra == "doc"
Requires-Dist: sphinxcontrib-trio; extra == "doc"
